sentry_deduplicate_integration/__init__.py
sentry_deduplicate_integration/integration.py
sentry_deduplicate_integration/tests/__init__.py
sentry_deduplicate_integration/tests/test_integration.py
sentry_deduplicate_integration-0.1.0.dist-info/METADATA
sentry_deduplicate_integration-0.1.0.dist-info/WHEEL
sentry_deduplicate_integration-0.1.0.dist-info/RECORD
