Metadata-Version: 2.1
Name: sentry-deduplicate-integration
Version: 0.1.0
Summary: 
Author: Iuri de Silvio
Author-email: iurisilvio@gmail.com
Requires-Python: >=3.10,<4.0
Classifier: Programming Language :: Python :: 3
Classifier: Programming Language :: Python :: 3.10
Classifier: Programming Language :: Python :: 3.11
Requires-Dist: sentry-sdk (>=1.12.0,<2.0.0)
